{
    "version": "https://jsonfeed.org/version/1",
    "title": "艾瑞可erik • All posts by \"世界那么大\" tag • All posts by \"undefined\" categories",
    "description": "一只PHP开发的程序猿，偶尔做做运维、Goland、Python、Java、摄影、画画、写作、顺便睡觉，反正整站都搞过。",
    "home_page_url": "https://erik.xyz",
    "items": [
        {
            "id": "https://erik.xyz/2015/04/25/shi-jie-na-me-da/",
            "url": "https://erik.xyz/2015/04/25/shi-jie-na-me-da/",
            "title": "世界那么大",
            "date_published": "2015-04-25T00:55:00.000Z",
            "content_html": "<p>世界那么大，我想有个家，陪你到白发。 </p>\n<p>世界那么大，女神已出嫁，剩我一个家。 </p>\n<p>世界那么大，还好我有家，因为有爸妈。 </p>\n<p>世界那么大，事非总还价，无奈不当大。</p>\n",
            "tags": [
                "世界那么大"
            ]
        }
    ]
}